tabixpy/LICENSE.txt
tabixpy/README.md
tabixpy/VERSION
tabixpy/__init__.py
tabixpy/_consts.py
tabixpy/_gzip.py
tabixpy/_io.py
tabixpy/_logger.py
tabixpy/_main.py
tabixpy/_tabix.py
tabixpy/_vcfbgzpy.py
tabixpy/tabixpy.py
tabixpy/tests/README.md
tabixpy/tests/annotated_tomato_150.100000.vcf.gz
tabixpy/tests/annotated_tomato_150.100000.vcf.gz.tbi
tabixpy/tests/annotated_tomato_150.SL2.50ch00-01-02.sh
tabixpy/tests/annotated_tomato_150.SL2.50ch00-01-02.vcf.gz
tabixpy/tests/annotated_tomato_150.SL2.50ch00-01-02.vcf.gz.tbi
tabixpy/tests/annotated_tomato_150.vcf.bgz.tbi
tabixpy/tests/run.sh
tabixpy/tests/test.py
tabixpy-1.5.2.dist-info/LICENSE.txt
tabixpy-1.5.2.dist-info/METADATA
tabixpy-1.5.2.dist-info/WHEEL
tabixpy-1.5.2.dist-info/entry_points.txt
tabixpy-1.5.2.dist-info/top_level.txt
tabixpy-1.5.2.dist-info/RECORD
