Metadata-Version: 2.1
Name: tabixpy
Version: 1.5.2
Summary: Tabix reader written 100% in Python
Home-page: https://github.com/bejobioinformatics/tabixpy
Author: Saulo Aflitos
Author-email: saulobejo@users.noreply.github.com
License: UNKNOWN
Keywords: Tabix Genomics VCF SNP
Platform: UNKNOWN
Classifier: Programming Language :: Python :: 3
Classifier: License :: OSI Approved :: MIT License
Classifier: Operating System :: OS Independent
Requires-Python: >=3.6
